minos/common/__init__.py
minos/common/builders.py
minos/common/config/__init__.py
minos/common/config/abc.py
minos/common/config/v1.py
minos/common/config/v2.py
minos/common/database/__init__.py
minos/common/database/clients/__init__.py
minos/common/database/clients/abc.py
minos/common/database/clients/exceptions.py
minos/common/database/locks/__init__.py
minos/common/database/locks/factories.py
minos/common/database/locks/impl.py
minos/common/database/managements.py
minos/common/database/mixins.py
minos/common/database/operations.py
minos/common/database/pools.py
minos/common/datetime.py
minos/common/exceptions.py
minos/common/importlib.py
minos/common/injections/__init__.py
minos/common/injections/decorators.py
minos/common/injections/injectors.py
minos/common/injections/mixins.py
minos/common/launchers.py
minos/common/locks.py
minos/common/meta.py
minos/common/model/__init__.py
minos/common/model/abc.py
minos/common/model/declarative.py
minos/common/model/dynamic/__init__.py
minos/common/model/dynamic/abc.py
minos/common/model/dynamic/bucket.py
minos/common/model/dynamic/dto.py
minos/common/model/fields.py
minos/common/model/serializers/__init__.py
minos/common/model/serializers/abc.py
minos/common/model/serializers/avro/__init__.py
minos/common/model/serializers/avro/data/__init__.py
minos/common/model/serializers/avro/data/decoder.py
minos/common/model/serializers/avro/data/encoder.py
minos/common/model/serializers/avro/schema/__init__.py
minos/common/model/serializers/avro/schema/constants.py
minos/common/model/serializers/avro/schema/decoder.py
minos/common/model/serializers/avro/schema/encoder.py
minos/common/model/types/__init__.py
minos/common/model/types/builders.py
minos/common/model/types/comparators.py
minos/common/model/types/constants.py
minos/common/model/types/generics.py
minos/common/model/types/model_types.py
minos/common/object.py
minos/common/pools.py
minos/common/ports.py
minos/common/protocol/__init__.py
minos/common/protocol/abc.py
minos_microservice_common-0.7.0.dist-info/LICENSE
minos_microservice_common-0.7.0.dist-info/WHEEL
minos_microservice_common-0.7.0.dist-info/METADATA
minos_microservice_common-0.7.0.dist-info/RECORD
