Metadata-Version: 2.1
Name: minos-microservice-common
Version: 0.7.0
Summary: The common core of the Minos Framework
Home-page: https://www.minos.run
License: MIT
Keywords: clariteia,minos,microservice,saga
Author: Minos Framework Devs
Author-email: hey@minos.run
Requires-Python: >=3.9,<4.0
Classifier: Development Status :: 4 - Beta
Classifier: Intended Audience :: Developers
Classifier: License :: OSI Approved :: MIT License
Classifier: Natural Language :: English
Classifier: Programming Language :: Python :: 3
Classifier: Programming Language :: Python :: 3.10
Classifier: Programming Language :: Python :: 3.9
Requires-Dist: PyYAML (>=5.4.1,<7.0.0)
Requires-Dist: aiomisc (>=14.0.3,<15.8.0)
Requires-Dist: cached-property (>=1.5.2,<2.0.0)
Requires-Dist: dependency-injector (>=4.32.2,<5.0.0)
Requires-Dist: fastavro (>=1.4.0,<2.0.0)
Requires-Dist: orjson (>=3.5.2,<4.0.0)
Requires-Dist: uvloop (>=0.16.0,<0.17.0)
Project-URL: Repository, https://github.com/minos-framework/minos-python
